MANIFEST.in
README.rst
setup.py
osinfo/__init__.py
osinfo/osinfo.py
py_osinfo.egg-info/PKG-INFO
py_osinfo.egg-info/SOURCES.txt
py_osinfo.egg-info/dependency_links.txt
py_osinfo.egg-info/top_level.txt