Metadata-Version: 1.1
Name: py-osinfo
Version: 0.1.1
Summary: A module for getting the OS type, brand, release, and kernel with Python 2 & 3
Home-page: https://github.com/workhorsy/py-osinfo
Author: Matthew Brennan Jones
Author-email: matthew.brennan.jones@gmail.com
License: MIT
Platform: UNKNOWN
Classifier: Development Status :: 4 - Beta
Classifier: Topic :: Utilities
Classifier: License :: OSI Approved :: MIT License
